rich_traceback/__init__.py
rich_traceback/enable.py
rich_traceback/formatter.py
rich_traceback/log.py
rich_traceback-1.0.3.dist-info/LICENSE
rich_traceback-1.0.3.dist-info/METADATA
rich_traceback-1.0.3.dist-info/WHEEL
rich_traceback-1.0.3.dist-info/top_level.txt
rich_traceback-1.0.3.dist-info/RECORD
